matchms/Fingerprints.py
matchms/Fragments.py
matchms/Metadata.py
matchms/Pipeline.py
matchms/Scores.py
matchms/Spectrum.py
matchms/Spikes.py
matchms/__init__.py
matchms/__version__.py
matchms/calculate_scores.py
matchms/constants.py
matchms/data/example_pipelines/library_cleaning.yaml
matchms/data/export_key_conversions.csv
matchms/data/known_adduct_conversions.csv
matchms/data/known_adducts_table.csv
matchms/data/known_key_conversions.csv
matchms/exporting/__init__.py
matchms/exporting/metadata_export.py
matchms/exporting/save_as_json.py
matchms/exporting/save_as_mgf.py
matchms/exporting/save_as_msp.py
matchms/exporting/save_as_mzspeclib.py
matchms/exporting/save_spectra.py
matchms/filtering/SpeciesString.py
matchms/filtering/SpectrumProcessor.py
matchms/filtering/__init__.py
matchms/filtering/default_filters.py
matchms/filtering/default_pipelines.py
matchms/filtering/filter_order.py
matchms/filtering/filter_utils/__init__.py
matchms/filtering/filter_utils/derive_precursor_mz_and_parent_mass.py
matchms/filtering/filter_utils/get_neutral_mass_from_smiles.py
matchms/filtering/filter_utils/interpret_unknown_adduct.py
matchms/filtering/filter_utils/load_known_adducts.py
matchms/filtering/filter_utils/smile_inchi_inchikey_conversions.py
matchms/filtering/metadata_processing/__init__.py
matchms/filtering/metadata_processing/add_compound_name.py
matchms/filtering/metadata_processing/add_fingerprint.py
matchms/filtering/metadata_processing/add_parent_mass.py
matchms/filtering/metadata_processing/add_precursor_mz.py
matchms/filtering/metadata_processing/add_retention.py
matchms/filtering/metadata_processing/clean_adduct.py
matchms/filtering/metadata_processing/clean_compound_name.py
matchms/filtering/metadata_processing/correct_charge.py
matchms/filtering/metadata_processing/derive_adduct_from_name.py
matchms/filtering/metadata_processing/derive_annotation_from_compound_name.py
matchms/filtering/metadata_processing/derive_formula_from_name.py
matchms-0.30.2.dist-info/LICENSE
matchms-0.30.2.dist-info/METADATA
matchms-0.30.2.dist-info/WHEEL
matchms-0.30.2.dist-info/RECORD
