Metadata-Version: 2.3
Name: matchms
Version: 0.30.2
Summary: Python library for large-scale comparisons and processing of tandem mass spectral data
License: Apache-2.0
Keywords: similarity measures,mass spectrometry,fuzzy matching,fuzzy search
Author: matchms developer team
Author-email: florian.huber@hs-duesseldorf.de
Requires-Python: >=3.10,<3.14
Classifier: Development Status :: 4 - Beta
Classifier: Intended Audience :: Developers
Classifier: Intended Audience :: Education
Classifier: Intended Audience :: Science/Research
Classifier: License :: OSI Approved :: Apache Software License
Classifier: Natural Language :: English
Classifier: Programming Language :: Python :: 3
Classifier: Programming Language :: Python :: 3.10
Classifier: Programming Language :: Python :: 3.11
Classifier: Programming Language :: Python :: 3.12
Classifier: Programming Language :: Python :: 3.13
Requires-Dist: deprecated (>=1.2.14)
Requires-Dist: lxml (>=5.4.0,<6.0.0)
Requires-Dist: matplotlib (>=3.7)
Requires-Dist: networkx (>=3.4.2,<4.0.0)
Requires-Dist: numba (>=0.61.0,<0.62.0)
Requires-Dist: numpy (>=2.0.0)
Requires-Dist: pandas (>=2.2.3,<3.0.0)
Requires-Dist: pickydict (>=0.4.0)
Requires-Dist: pillow (!=9.4.0)
Requires-Dist: pubchempy
Requires-Dist: pynndescent (>=0.5.13)
Requires-Dist: pyteomics (>=4.6)
Requires-Dist: pyyaml (>=6.0.1)
Requires-Dist: rdkit (>=2024.3.5,<2025.0.0)
Requires-Dist: requests (>=2.31.0)
Requires-Dist: scipy (>=1.15.3,<2.0.0)
Requires-Dist: sparsestack (>=0.7.0)
Requires-Dist: tqdm (>=4.65.0)
Project-URL: Documentation, https://matchms.readthedocs.io/en/latest/
Project-URL: Repository, https://github.com/matchms/matchms
